postgres/__init__.py
postgres/cache.py
postgres/context_managers.py
postgres/cursors.py
postgres/orm.py
postgres-4.0.dist-info/LICENSE
postgres-4.0.dist-info/METADATA
postgres-4.0.dist-info/WHEEL
postgres-4.0.dist-info/top_level.txt
postgres-4.0.dist-info/RECORD
